<annotation>
	<folder>1</folder>
	<filename>001590.jpg</filename>
	<path>C:\Users\user\Desktop\1\001590.jpg</path>
	<source>
		<database>Unknown</database>
	</source>
	<size>
		<width>161</width>
		<height>300</height>
		<depth>3</depth>
	</size>
	<segmented>0</segmented>
	<object>
		<name>do_not_bleach</name>
		<pose>Unspecified</pose>
		<truncated>0</truncated>
		<difficult>0</difficult>
		<bndbox>
			<xmin>72</xmin>
			<ymin>166</ymin>
			<xmax>99</xmax>
			<ymax>191</ymax>
		</bndbox>
	</object>
	<object>
		<name>do_not_dry_clean</name>
		<pose>Unspecified</pose>
		<truncated>0</truncated>
		<difficult>0</difficult>
		<bndbox>
			<xmin>86</xmin>
			<ymin>195</ymin>
			<xmax>111</xmax>
			<ymax>214</ymax>
		</bndbox>
	</object>
</annotation>
