<annotation>
	<folder>닭</folder>
	<filename>001629.jpg</filename>
	<path>C:\Users\Leejunsoo\Desktop\닭\001629.jpg</path>
	<source>
		<database>Unknown</database>
	</source>
	<size>
		<width>600</width>
		<height>600</height>
		<depth>3</depth>
	</size>
	<segmented>0</segmented>
	<object>
		<name>do_not_dry_clean</name>
		<pose>Unspecified</pose>
		<truncated>0</truncated>
		<difficult>0</difficult>
		<bndbox>
			<xmin>283</xmin>
			<ymin>258</ymin>
			<xmax>334</xmax>
			<ymax>311</ymax>
		</bndbox>
	</object>
	<object>
		<name>do_not_bleach</name>
		<pose>Unspecified</pose>
		<truncated>0</truncated>
		<difficult>0</difficult>
		<bndbox>
			<xmin>169</xmin>
			<ymin>247</ymin>
			<xmax>220</xmax>
			<ymax>298</ymax>
		</bndbox>
	</object>
</annotation>
